trecover/__init__.py
trecover/model.py
trecover/app/__init__.py
trecover/app/dashboard.py
trecover/app/api/__init__.py
trecover/app/api/schemas.py
trecover/app/api/trecoverapi.py
trecover/app/api/backend/__init__.py
trecover/app/api/backend/celeryapp.py
trecover/app/api/backend/tasks.py
trecover/app/api/backend/tasksbase.py
trecover/app/cli/__init__.py
trecover/app/cli/api.py
trecover/app/cli/backend.py
trecover/app/cli/broker.py
trecover/app/cli/dashboard.py
trecover/app/cli/download.py
trecover/app/cli/mlflow.py
trecover/app/cli/train.py
trecover/app/cli/trecovercli.py
trecover/app/cli/worker.py
trecover/config/__init__.py
trecover/config/exp_var.py
trecover/config/log.py
trecover/config/var.py
trecover/train/__init__.py
trecover/train/data.py
trecover/train/local.py
trecover/train/loss.py
trecover/train/monitor.py
trecover/train/scheduler.py
trecover/train/trainer.py
trecover/utils/__init__.py
trecover/utils/beam_search.py
trecover/utils/cli.py
trecover/utils/data.py
trecover/utils/docker.py
trecover/utils/inference.py
trecover/utils/model.py
trecover/utils/train.py
trecover/utils/transform.py
trecover/utils/visualization.py
trecover-1.0.3.dist-info/LICENSE
trecover-1.0.3.dist-info/METADATA
trecover-1.0.3.dist-info/WHEEL
trecover-1.0.3.dist-info/entry_points.txt
trecover-1.0.3.dist-info/top_level.txt
trecover-1.0.3.dist-info/RECORD
